<?xml version="1.0" encoding="UTF-8"?>
<!-- Created with TexturePacker http://texturepacker.com-->
<!-- $TexturePacker:SmartUpdate:93a419d802924a8bc47b28d21398c7d5$ -->
<TextureAtlas imagePath="ChineseChess.png">
    <SubTexture name="BLUE" x="2" y="2" width="117" height="99"/>
    <SubTexture name="BLUE_BISHOP" x="121" y="2" width="54" height="71"/>
    <SubTexture name="BLUE_CANNON" x="177" y="2" width="54" height="71"/>
    <SubTexture name="BLUE_KNIGHT" x="2" y="103" width="54" height="71"/>
    <SubTexture name="BLUE_MARSHAL" x="58" y="103" width="54" height="71"/>
    <SubTexture name="BLUE_OFFICAL" x="114" y="103" width="54" height="71"/>
    <SubTexture name="BLUE_PAWN" x="170" y="103" width="54" height="71"/>
    <SubTexture name="BLUE_ROOK" x="2" y="176" width="54" height="71"/>
    <SubTexture name="RED" x="58" y="176" width="119" height="105"/>
    <SubTexture name="RED_BISHOP" x="179" y="176" width="54" height="71"/>
    <SubTexture name="RED_CANNON" x="2" y="283" width="54" height="71"/>
    <SubTexture name="RED_KNIGHT" x="58" y="283" width="54" height="71"/>
    <SubTexture name="RED_MARSHAL" x="114" y="283" width="54" height="71"/>
    <SubTexture name="RED_OFFICAL" x="170" y="283" width="54" height="71"/>
    <SubTexture name="RED_PAWN" x="2" y="356" width="54" height="71"/>
    <SubTexture name="RED_ROOK" x="58" y="356" width="54" height="71"/>
</TextureAtlas>
